fqllang/Pipfile
fqllang/Pipfile.lock
fqllang/__init__.py
fqllang/core.py
fqllang/requirements.txt
fqllang/fql_stage/__init__.py
fqllang/fql_stage/ast_builders.py
fqllang/fql_stage/utils.py
fqllang/fql_stage/analizers/base.py
fqllang/fql_stage/analizers/create_form.py
fqllang/fql_stage/analizers/fql_statements.py
fqllang/fql_stage/components/basic_components.py
fqllang/fql_stage/components/create_form.py
fqllang/fql_stage/components/create_new.py
fqllang/fql_stage/components/dataconstraints.py
fqllang/fql_stage/components/datatypes.py
fqllang/fql_stage/components/refcardinalities.py
fqllang/fql_stage/grammar/createForm.tx
fqllang/fql_stage/grammar/createNew.tx
fqllang/fql_stage/grammar/fqlgrammar.tx
fqllang/fql_stage/grammar/getCase.tx
fqllang/fql_stage/grammar/keywords.tx
fqllang/fql_stage/grammar/showForms.tx
fqllang/fql_stage/grammar/valueTerminal.tx
fqllang/sql_stage/__init__.py
fqllang/sql_stage/code_generators/__init__.py
fqllang/sql_stage/code_generators/basic_elements.py
fqllang/sql_stage/code_generators/create.py
fqllang/sql_stage/code_generators/insert.py
fqllang/sql_stage/code_generators/main_elements.py
fqllang/sql_stage/code_generators/select.py
fqllang/sql_stage/code_transpilers/__init__.py
fqllang/sql_stage/code_transpilers/postgreTranspiler.py
fqllang/sql_stage/code_transpilers/transpiler.py
fqllang/sql_stage/components/basic_components.py
fqllang/sql_stage/components/create_table.py
fqllang/sql_stage/components/dataconstraints.py
fqllang/sql_stage/components/datatypes.py
fqllang/tests/test_fqlstage/test_builders.py
fqllang/tests/test_fqlstage/test_components/test_basic_components.py
fqllang/tests/test_fqlstage/test_components/test_create_form.py
fqllang/tests/test_sqlstage/test_code_generators/test_create.py
fqllang/tests/test_sqlstage/test_code_generators/test_elements.py
fqllang/tests/test_sqlstage/test_code_generators/test_insert.py
fqllang/tests/test_sqlstage/test_code_generators/test_select.py
fqllang-0.9.0.dist-info/METADATA
fqllang-0.9.0.dist-info/WHEEL
fqllang-0.9.0.dist-info/licenses/LICENSE
fqllang-0.9.0.dist-info/RECORD
