Metadata-Version: 2.1
Name: fqllang
Version: 0.9.0
Summary: Fql Transpiler
Author-email: Leandro Hernandez <leandro.nunez1457@gmail.com>
License-File: LICENSE
Classifier: License :: OSI Approved :: MIT License
Classifier: Operating System :: OS Independent
Classifier: Programming Language :: Python :: 3
Requires-Python: >=3.7
Requires-Dist: enums-py
Requires-Dist: textx
